[
    {
      "_id": "64783eab84cf8841e625a9b7",
      "isActive": true,
      "category_unique_name": "cleaning-supplies",
      "img": "https://i.ibb.co/TMthNp1/Trix-Dishwashing-Liquid-Double-Pack-250ml-min-copy.png",
      "category_name": "Ceaning Supplies",
      "sub_category": [
        {
          "sub_cat_id": "ffffff",
          "img": "https://i.ibb.co/TMthNp1/Trix-Dishwashing-Liquid-Double-Pack-250ml-min-copy.png",
          "sub_category_unique_name": "cleaning",
          "sub_category_name": "Washing & cleaning",
          "isActive": false
        },
        {
          "sub_cat_id": "eeeee",
          "sub_category_unique_name": "fresh",
          "img": "https://i.ibb.co/TMthNp1/Trix-Dishwashing-Liquid-Double-Pack-250ml-min-copy.png",
          "sub_category_name": "freshing agents",
          "isActive": true
        }
     
      ]
    },
    {
      "_id": "64783eabd1d683c9d4b6e88b",
      "isActive": true,
      "category_unique_name": "nisi",
      "img": "https://i.ibb.co/TMthNp1/Trix-Dishwashing-Liquid-Double-Pack-250ml-min-copy.png",
      "category_name": "gol alu",
      "sub_category": [
        {
          "sub_cat_id": "ddddd",
          "sub_category_unique_name": "cleaning",
          "img": "https://i.ibb.co/TMthNp1/Trix-Dishwashing-Liquid-Double-Pack-250ml-min-copy.png",
          "sub_category_name": "Washing & cleaning",
          "isActive": false
        },
        {
          "sub_cat_id": "ccccc",
          "sub_category_unique_name": "fresh",
          "img": "https://i.ibb.co/TMthNp1/Trix-Dishwashing-Liquid-Double-Pack-250ml-min-copy.png",
          "sub_category_name": "freshing agents",
          "isActive": true
        }
      ]
    },
    {
      "_id": "64783eab6dcf7b5152f1131c",
      "isActive": false,
      "category_unique_name": "cillum",
      "img": "https://i.ibb.co/TMthNp1/Trix-Dishwashing-Liquid-Double-Pack-250ml-min-copy.png",
      "category_name": "misti alu",
      "sub_category": [
        {
          "sub_cat_id": "bbbbb",
          "sub_category_unique_name": "cleaning",
          "img": "https://i.ibb.co/TMthNp1/Trix-Dishwashing-Liquid-Double-Pack-250ml-min-copy.png",
          "sub_category_name": "Washing & cleaning",
          "isActive": false
        },
        {
          "sub_cat_id": "aaaaa",
          "sub_category_unique_name": "fresh",
          "img": "https://i.ibb.co/TMthNp1/Trix-Dishwashing-Liquid-Double-Pack-250ml-min-copy.png",
          "sub_category_name": "freshing agents",
          "isActive": true
        }
      ]
    },
    {
      "_id": "ksdajfjlsdjfaaajlksdajlfkjdsaflk",
      "isActive": false,
      "category_unique_name": "cillum",
      "img": "https://i.ibb.co/TMthNp1/Trix-Dishwashing-Liquid-Double-Pack-250ml-min-copy.png",
      "category_name": "choto alu",
      "path" : "cleaning",
      "sub_category": [
       
      ]
    },
    {
      "_id": "ksdajfjlsdjaafjlksdajlfkjdsaflk",
      "isActive": false,
      "category_unique_name": "cillum",
      "img": "https://i.ibb.co/TMthNp1/Trix-Dishwashing-Liquid-Double-Pack-250ml-min-copy.png",
      "category_name": "choto alu",
      "path" : "cleaning",
      "sub_category": [
       
      ]
    },
    {
      "_id": "ksdajfjlsdjfjlksdadffjlfkjdsaflk",
      "isActive": false,
      "category_unique_name": "cillum",
      "img": "https://i.ibb.co/TMthNp1/Trix-Dishwashing-Liquid-Double-Pack-250ml-min-copy.png",
      "category_name": "choto alu",
      "path" : "cleaning",
      "sub_category": [
       
      ]
    },
    {
      "_id": "ksdajfjlsdjfjlkfsdajldffsdfkjdsaflk",
      "isActive": false,
      "category_unique_name": "cillum",
      "img": "https://i.ibb.co/TMthNp1/Trix-Dishwashing-Liquid-Double-Pack-250ml-min-copy.png",
      "category_name": "choto alu",
      "path" : "cleaning",
      "sub_category": [
       
      ]
    },
    {
      "_id": "ksdajfjalsdjfjldfksdajlfkjdsaflk",
      "isActive": false,
      "category_unique_name": "cillum",
      "img": "https://i.ibb.co/TMthNp1/Trix-Dishwashing-Liquid-Double-Pack-250ml-min-copy.png",
      "category_name": "choto alu",
      "path" : "cleaning",
      "sub_category": [
       
      ]
    },
    {
      "_id": "ksdajfjalsdjfjldfkdsdajlfkjdsaflk",
      "isActive": false,
      "category_unique_name": "cillum",
      "img": "https://i.ibb.co/TMthNp1/Trix-Dishwashing-Liquid-Double-Pack-250ml-min-copy.png",
      "category_name": "choto alu",
      "path" : "cleaning",
      "sub_category": [
       
      ]
    },
    {
      "_id": "ksdajfjalgsdjfjldfksdajlfkjdsaflk",
      "isActive": false,
      "category_unique_name": "cillum",
      "img": "https://i.ibb.co/TMthNp1/Trix-Dishwashing-Liquid-Double-Pack-250ml-min-copy.png",
      "category_name": "choto alu",
      "path" : "cleaning",
      "sub_category": [
       
      ]
    },
    {
      "_id": "ksdajfjalsdjfjldnfksdajlfkjdsaflk",
      "isActive": false,
      "category_unique_name": "cillum",
      "img": "https://i.ibb.co/TMthNp1/Trix-Dishwashing-Liquid-Double-Pack-250ml-min-copy.png",
      "category_name": "choto alu",
      "path" : "cleaning",
      "sub_category": [
       
      ]
    },
    {
      "_id": "ksdajfjalsdjfjldfnnksdajlfkjdsaflk",
      "isActive": false,
      "category_unique_name": "cillum",
      "img": "https://i.ibb.co/TMthNp1/Trix-Dishwashing-Liquid-Double-Pack-250ml-min-copy.png",
      "category_name": "choto alu",
      "path" : "cleaning",
      "sub_category": [
       
      ]
    },
    {
      "_id": "ksdajfjalsdjfjldnnnfksdajlfkjdsaflk",
      "isActive": false,
      "category_unique_name": "cillum",
      "img": "https://i.ibb.co/TMthNp1/Trix-Dishwashing-Liquid-Double-Pack-250ml-min-copy.png",
      "category_name": "choto alu",
      "path" : "cleaning",
      "sub_category": [
       
      ]
    },
    {
      "_id": "ksdajfjalsdjfjttldfksdajlfkjdsaflk",
      "isActive": false,
      "category_unique_name": "cillum",
      "img": "https://i.ibb.co/TMthNp1/Trix-Dishwashing-Liquid-Double-Pack-250ml-min-copy.png",
      "category_name": "choto alu",
      "path" : "cleaning",
      "sub_category": [
       
      ]
    },
    {
      "_id": "ksdajfjalsdjfjldfktrrsdajlfkjdsaflk",
      "isActive": false,
      "category_unique_name": "cillum",
      "img": "https://i.ibb.co/TMthNp1/Trix-Dishwashing-Liquid-Double-Pack-250ml-min-copy.png",
      "category_name": "choto alu",
      "path" : "cleaning",
      "sub_category": [
       
      ]
    },
    {
      "_id": "ksdajfjalsdjfjldfksfghdajlfkjdsaflk",
      "isActive": false,
      "category_unique_name": "cillum",
      "img": "https://i.ibb.co/TMthNp1/Trix-Dishwashing-Liquid-Double-Pack-250ml-min-copy.png",
      "category_name": "choto alu",
      "path" : "cleaning",
      "sub_category": [
       
      ]
    },
    {
      "_id": "ksdajfjalsdjfjldfksdhghajlfkjdsaflk",
      "isActive": false,
      "category_unique_name": "cillum",
      "img": "https://i.ibb.co/TMthNp1/Trix-Dishwashing-Liquid-Double-Pack-250ml-min-copy.png",
      "category_name": "choto alu",
      "path" : "cleaning",
      "sub_category": [
       
      ]
    },
    {
      "_id": "ksdahgjfjalsdjfjldfksdajlfkjdsaflk",
      "isActive": false,
      "category_unique_name": "cillum",
      "img": "https://i.ibb.co/TMthNp1/Trix-Dishwashing-Liquid-Double-Pack-250ml-min-copy.png",
      "category_name": "choto alu",
      "path" : "cleaning",
      "sub_category": [
       
      ]
    },
    {
      "_id": "ksdajfjalsdjfjldfksdajlfkjdsghaflk",
      "isActive": false,
      "category_unique_name": "cillum",
      "img": "https://i.ibb.co/TMthNp1/Trix-Dishwashing-Liquid-Double-Pack-250ml-min-copy.png",
      "category_name": "choto alu",
      "path" : "cleaning",
      "sub_category": [
       
      ]
    },
    {
      "_id": "kghsdajfjalsdjfjldfksdajlfkjdsaflk",
      "isActive": false,
      "category_unique_name": "cillum",
      "img": "https://i.ibb.co/TMthNp1/Trix-Dishwashing-Liquid-Double-Pack-250ml-min-copy.png",
      "category_name": "choto alu",
      "path" : "cleaning",
      "sub_category": [
       
      ]
    },
    {
      "_id": "kshgdajfjalsdjfjldfksdajlfkjdsaflk",
      "isActive": false,
      "category_unique_name": "cillum",
      "img": "https://i.ibb.co/TMthNp1/Trix-Dishwashing-Liquid-Double-Pack-250ml-min-copy.png",
      "category_name": "choto alu",
      "path" : "cleaning",
      "sub_category": [
       
      ]
    },
    {
      "_id": "ksdajfhgjalsdjfjldfksdajlfkjdsaflk",
      "isActive": false,
      "category_unique_name": "cillum",
      "img": "https://i.ibb.co/TMthNp1/Trix-Dishwashing-Liquid-Double-Pack-250ml-min-copy.png",
      "category_name": "choto alu",
      "path" : "cleaning",
      "sub_category": [
       
      ]
    },
    {
      "_id": "ksdajfjlshgdjfjlksdabjlfkjdsaflk",
      "isActive": false,
      "category_unique_name": "cillum",
      "img": "https://i.ibb.co/TMthNp1/Trix-Dishwashing-Liquid-Double-Pack-250ml-min-copy.png",
      "category_name": "choto alu",
      "path" : "cleaning",
      "sub_category": [
       
      ]
    }
  ]